langtune/__init__.py
langtune/acceleration.py
langtune/api.py
langtune/auth.py
langtune/callbacks.py
langtune/cli.py
langtune/client.py
langtune/config.py
langtune/data.py
langtune/data_engine.py
langtune/device.py
langtune/distributed.py
langtune/facade.py
langtune/finetune.py
langtune/generation.py
langtune/logging_utils.py
langtune/metrics.py
langtune/models.py
langtune/optimizations.py
langtune/py.typed
langtune/remote.py
langtune/rich_help.py
langtune/schedulers.py
langtune/tokenizers.py
langtune/trainer.py
langtune/utils.py
langtune/worker.py
langtune/model/__init__.py
langtune/model/hub.py
langtune/model/kernels.py
langtune/model/loader.py
langtune/model/safetensors.py
langtune/model/weights.py
langtune/nn/fast_transformer.py
langtune/nn/layers.py
langtune/nn/transformer.py
langtune/training/neftune.py
langtune-0.1.35.dist-info/licenses/LICENSE
langtune-0.1.35.dist-info/METADATA
langtune-0.1.35.dist-info/WHEEL
langtune-0.1.35.dist-info/entry_points.txt
langtune-0.1.35.dist-info/top_level.txt
langtune-0.1.35.dist-info/RECORD
