Metadata-Version: 2.4
Name: langtune
Version: 0.1.35
Summary: Efficient LoRA Fine-Tuning for Large Language Models - Train smarter, not harder.
Author-email: Pritesh Raj <priteshraj41@gmail.com>
Maintainer-email: Langtrain AI <contact@langtrain.ai>
License: MIT License
Project-URL: Homepage, https://github.com/langtrain-ai/langtune
Project-URL: Documentation, https://github.com/langtrain-ai/langtune/tree/main/docs
Project-URL: Repository, https://github.com/langtrain-ai/langtune
Project-URL: Changelog, https://github.com/langtrain-ai/langtune/blob/main/CHANGELOG.md
Project-URL: Bug Tracker, https://github.com/langtrain-ai/langtune/issues
Keywords: llm,lora,fine-tuning,machine-learning,deep-learning,transformers,nlp,language-model,pytorch,rlhf,dpo,ppo
Classifier: Development Status :: 4 - Beta
Classifier: Intended Audience :: Developers
Classifier: Intended Audience :: Science/Research
Classifier: License :: OSI Approved :: MIT License
Classifier: Operating System :: OS Independent
Classifier: Programming Language :: Python :: 3
Classifier: Programming Language :: Python :: 3.8
Classifier: Programming Language :: Python :: 3.9
Classifier: Programming Language :: Python :: 3.10
Classifier: Programming Language :: Python :: 3.11
Classifier: Programming Language :: Python :: 3.12
Classifier: Topic :: Scientific/Engineering :: Artificial Intelligence
Classifier: Topic :: Software Development :: Libraries :: Python Modules
Classifier: Typing :: Typed
Requires-Python: >=3.8
License-File: LICENSE
Requires-Dist: torch>=1.10
Requires-Dist: numpy
Requires-Dist: tqdm
Requires-Dist: pyyaml
Requires-Dist: scipy
Requires-Dist: wandb
Requires-Dist: rich>=13.0.0
Provides-Extra: dev
Requires-Dist: pytest>=7.0; extra == "dev"
Requires-Dist: pytest-cov; extra == "dev"
Requires-Dist: black; extra == "dev"
Requires-Dist: flake8; extra == "dev"
Requires-Dist: mypy; extra == "dev"
Requires-Dist: isort; extra == "dev"
Provides-Extra: all
Requires-Dist: transformers; extra == "all"
Requires-Dist: datasets; extra == "all"
Requires-Dist: accelerate; extra == "all"
Requires-Dist: bitsandbytes; extra == "all"
Dynamic: license-file
